example/__init__.py
example/contact.py
example/room.py
pyjuzi/__init__.py
pyjuzi/contact.py
pyjuzi/exception.py
pyjuzi/room.py
pyjuzi/transport.py
pyjuzi-0.0.1.dist-info/LICENSE
pyjuzi-0.0.1.dist-info/METADATA
pyjuzi-0.0.1.dist-info/WHEEL
pyjuzi-0.0.1.dist-info/top_level.txt
pyjuzi-0.0.1.dist-info/RECORD
