Metadata-Version: 2.1
Name: pyjuzi
Version: 0.0.1
Summary: juzi python sdk
Home-page: https://github.com/fatelei/pyjuzi
Author: fatelei
Author-email: fatelei@gmail.com
License: PRIVATE
Platform: UNKNOWN
